{"card_id": "31432da19bfb", "source_path": "ROUND_5/autoresearch/14_lag_research/O_submit/findings_v3.md", "phase_tag": "autoresearch/14_lag_research/O_submit", "ext": ".md", "products_mentioned": ["MICROCHIP_SQUARE", "PANEL_1X2", "PANEL_1X4", "PANEL_2X4", "PEBBLES_L", "PEBBLES_XL", "PEBBLES_XS", "SLEEP_POD_SUEDE"], "claim_summary": "Round 3 \u2014 Final findings", "h1": ["Round 3 \u2014 Final findings"], "h2": ["Headline", "What v3 adds: 30 cross-group cointegration pairs (Phase C)", "Phase scoreboard", "Per-product summary (3-day cumulative, top-30 v3)", "Critical conclusions", "Reproducing"], "key_numbers": {"sharpe": 0.7, "half_life": 5.0}, "evidence_type": "narrative", "tags": ["cointegration", "lead_lag", "basket", "mean_reversion", "ar1", "microstructure", "stat_test", "backtest"], "confidence": "medium", "size": 4095, "raw_excerpt": "# Round 3 \u2014 Final findings\n\n## Headline\n\n| Metric                           | v1     | v2     | v3 (final) | \u0394 vs v2  |\n|----------------------------------|--------|--------|------------|----------|\n| Total PnL, days 2\u20134 (worse)      | 396,749 | 531,525 | **733,320** | +201,795 |\n| Sharpe (merged)                  | 4.22   | 8.61   | **8.34**    | flat     |\n| Max DD abs                       | 30,772 | 26,286 | 23,990      | -2,296   |\n| Max DD %                         | 26.9 % | 5.0 %  | 21.9 %      | +16.9 ppt|\n| Per-day d2 / d3 / d4             | 125/105/167 K | 169/162/201 K | **234/278/222 K** | +65/+116/+21 K |\n| Match-mode band (worse vs all)   | 0      | 0      | 0           | identical |\n\n**v3 ships.** +201K (+38 %) over v2.\n\nDay 5 forecast (1 day): low \u2248 222K, base \u2248 244K, high"}