{"card_id": "70c1404814a5", "source_path": "ROUND_5/autoresearch/mr_study/02_threshold_search/per_product/PEBBLES_S/top20.csv", "phase_tag": "autoresearch/mr_study/02_threshold_search", "ext": ".csv", "products_mentioned": ["PEBBLES_S"], "claim_summary": "CSV n=20 cols=20 sort_col=avg_daily_pnl", "columns": ["product", "fv_id", "rule", "z_in", "z_out", "z_stop", "time_stop", "sizing", "sizing_gamma", "pnl_A", "pnl_B", "sharpe_A", "sharpe_B", "nt_A", "nt_B", "dd_A", "dd_B", "avg_daily_pnl", "min_pnl", "min_sharpe"], "n_rows": 20, "top_rows": [{"product": "PEBBLES_S", "fv_id": "ewma_50", "rule": "A", "z_in": 1.25, "z_out": 0.0, "z_stop": -1.0, "time_stop": -1, "sizing": "fixed", "sizing_gamma": 0.0, "pnl_A": 12323.0, "pnl_B": -12966.0, "sharpe_A": 1.476647040600915, "sharpe_B": -1.2878209513125252, "nt_A": 121, "nt_B": 126, "dd_A": 9719.0, "dd_B": 21726.0, "avg_daily_pnl": -321.5, "min_pnl": -12966.0, "min_sharpe": -1.2878209513125252}, {"product": "PEBBLES_S", "fv_id": "ewma_50", "rule": "A", "z_in": 1.25, "z_out": 0.1, "z_stop": -1.0, "time_stop": -1, "sizing": "fixed", "sizing_gamma": 0.0, "pnl_A": 13067.0, "pnl_B": -14758.0, "sharpe_A": 1.5562352719151828, "sharpe_B": -1.4375475349703692, "nt_A": 130, "nt_B": 131, "dd_A": 10099.0, "dd_B": 21686.0, "avg_daily_pnl": -845.5, "min_pnl": -14758.0, "min_sharpe": -1.4375475349703692}, {"product": "PEBBLES_S", "fv_id": "ewma_50", "rule": "A", "z_in": 2.5, "z_out": 0.0, "z_stop": -1.0, "time_stop": -1, "sizing": "fixed", "sizing_gamma": 0.0, "pnl_A": 1595.0, "pnl_B": -3380.0, "sharpe_A": 0.8235251444975571, "sharpe_B": -0.6586222792103709, "nt_A": 7, "nt_B": 24, "dd_A": 2730.0, "dd_B": 9070.0, "avg_daily_pnl": -892.5, "min_pnl": -3380.0, "min_sharpe": -0.6586222792103709}], "evidence_type": "backtest", "tags": ["mean_reversion", "basket", "backtest"], "confidence": "high", "size": 3305}