{"card_id": "c7b1049511ab", "source_path": "ROUND_5/autoresearch/14_lag_research/C_lagged_coint/lagged_coint_surviving.csv", "phase_tag": "autoresearch/14_lag_research/C_lagged_coint", "ext": ".csv", "products_mentioned": [], "claim_summary": "CSV n=171 cols=14 sort_col=None", "columns": ["i", "j", "lag", "group_i", "group_j", "slope", "intercept", "adf_p", "ou_hl", "fA_sharpe", "fA_pnl", "fB_sharpe", "fB_pnl", "min_fold_sharpe"], "n_rows": 171, "top_rows": [{"i": "SNACKPACK_VANILLA", "j": "SNACKPACK_CHOCOLATE", "lag": 100, "group_i": "snackpack", "group_j": "snackpack", "slope": -0.7816128779826323, "intercept": 17791.784763517302, "adf_p": 6.233126422948692e-05, "ou_hl": 147.35360854597354, "fA_sharpe": 4.2468323681989775, "fA_pnl": 2678.4068647903605, "fB_sharpe": 2.841056021357965, "fB_pnl": 1407.8736695533917, "min_fold_sharpe": 2.841056021357965}, {"i": "SNACKPACK_CHOCOLATE", "j": "SNACKPACK_VANILLA", "lag": 100, "group_i": "snackpack", "group_j": "snackpack", "slope": -0.9707740650022284, "intercept": 19644.26450086045, "adf_p": 0.0005019173422594, "ou_hl": 173.89771671115503, "fA_sharpe": 2.8140686169710074, "fA_pnl": 2034.7929859252745, "fB_sharpe": 2.631959606161983, "fB_pnl": 1884.3178701975469, "min_fold_sharpe": 2.631959606161983}, {"i": "MICROCHIP_SQUARE", "j": "SLEEP_POD_SUEDE", "lag": 100, "group_i": "microchip", "group_j": "sleep_pod", "slope": 1.8491788283254749, "intercept": -7466.61592831549, "adf_p": 0.0067075768366941, "ou_hl": 845.2215638318196, "fA_sharpe": 2.437415738002815, "fA_pnl": 2479.774358656159, "fB_sharpe": 2.3844793031980305, "fB_pnl": 3503.2219824580025, "min_fold_sharpe": 2.3844793031980305}], "evidence_type": "backtest", "tags": ["mean_reversion", "stat_test", "backtest"], "confidence": "medium", "size": 38615}