{"card_id": "fac3b03a768e", "source_path": "ROUND_5/autoresearch/10_backtesting/results/5_2_all.csv", "phase_tag": "autoresearch/10_backtesting/results", "ext": ".csv", "products_mentioned": ["GALAXY_SOUNDS_BLACK_HOLES", "GALAXY_SOUNDS_DARK_MATTER", "GALAXY_SOUNDS_PLANETARY_RINGS", "GALAXY_SOUNDS_SOLAR_FLAMES", "GALAXY_SOUNDS_SOLAR_WINDS", "MICROCHIP_CIRCLE", "MICROCHIP_OVAL", "MICROCHIP_RECTANGLE"], "claim_summary": "CSV n=53 cols=2 sort_col=pnl", "columns": ["product", "pnl"], "n_rows": 53, "top_rows": [{"product": "__total__", "pnl": 124893.0}, {"product": "__max_drawdown_abs__", "pnl": 26980.0}, {"product": "GALAXY_SOUNDS_PLANETARY_RINGS", "pnl": 23252.0}], "describe": {"pnl": {"mean": 5222.049603773585, "max": 124893.0, "min": -11955.0}}, "evidence_type": "backtest", "tags": ["backtest"], "confidence": "high", "size": 1296, "raw_excerpt": ""}